setup.py
invoke_api/__init__.py
invoke_api/aliapi.py
invoke_api/hwapi.py
invoke_api.egg-info/PKG-INFO
invoke_api.egg-info/SOURCES.txt
invoke_api.egg-info/dependency_links.txt
invoke_api.egg-info/requires.txt
invoke_api.egg-info/top_level.txt