Metadata-Version: 2.1
Name: invoke-api
Version: 0.5.0
Summary: use ak and sk invoke huawei cloud http api
Author: karman
Author-email: 460312252@qq.com
Classifier: Programming Language :: Python :: 3
Classifier: License :: OSI Approved :: MIT License
Classifier: Operating System :: OS Independent
Requires-Python: >=3.6
